{
  "source": "PubMed",
  "query": "stilbenes",
  "title": "Use of raloxifene as a sequential therapy after romosozumab : an observational study.",
  "abstract": "There have been no studies on the effectiveness of raloxifene as an antiresorptive agentfollowing discontinuation of romosozumab. The aim of this study was to investigate the potential effectiveness of raloxifene following a romosozumab therapy.",
  "publication_date": "2025-04-01",
  "journal": "The journal of medical investigation : JMI",
  "doi": "10.2152/jmi.72.124"
}